mmh3.cpython-36m-x86_64-linux-gnu.so
mmh3_binary-2.5.1.dist-info/LICENSE
mmh3_binary-2.5.1.dist-info/METADATA
mmh3_binary-2.5.1.dist-info/RECORD
mmh3_binary-2.5.1.dist-info/WHEEL
mmh3_binary-2.5.1.dist-info/top_level.txt
