Metadata-Version: 2.1
Name: mmh3-binary
Version: 2.5.1
Summary: Python wrapper for MurmurHash (MurmurHash3), a set of fast and robust hash functions. With wheels!
Home-page: https://github.com/felipeochoa/mmh3
Author: Hajime Senuma
Author-email: hajime.senuma@gmail.com
License: License :: CC0 1.0 Universal (CC0 1.0) Public Domain Dedication
Keywords: utility hash MurmurHash wheel
Platform: UNKNOWN
Classifier: Development Status :: 5 - Production/Stable
Classifier: Intended Audience :: Developers
Classifier: License :: CC0 1.0 Universal (CC0 1.0) Public Domain Dedication
Classifier: Programming Language :: Python :: 2
Classifier: Programming Language :: Python :: 2.7
Classifier: Programming Language :: Python :: 3
Classifier: Programming Language :: Python :: 3.3
Classifier: Programming Language :: Python :: 3.4
Classifier: Programming Language :: Python :: 3.5
Classifier: Programming Language :: Python :: 3.6
Classifier: Topic :: Software Development :: Libraries
Classifier: Topic :: Utilities
